docs/developer-guide.md
docs/gen_ref_nav.py
docs/index.md
docs/install.md
docs/usage.md
run_time_assurance/__init__.py
run_time_assurance/constraint.py
run_time_assurance/controller.py
run_time_assurance/rta/__init__.py
run_time_assurance/rta/asif.py
run_time_assurance/rta/base.py
run_time_assurance/rta/simplex.py
run_time_assurance/state.py
run_time_assurance/utils/__init__.py
run_time_assurance/utils/sample_testing.py
run_time_assurance/utils/utils.py
run_time_assurance/zoo/__init__.py
run_time_assurance/zoo/cwh/__init__.py
run_time_assurance/zoo/cwh/docking_2d.py
run_time_assurance/zoo/cwh/docking_3d.py
run_time_assurance/zoo/cwh/inspection_1v1.py
run_time_assurance/zoo/cwh/inspection_3d.py
run_time_assurance/zoo/cwh/random_sample_testing.py
run_time_assurance/zoo/cwh/utils.py
run_time_assurance/zoo/integrators/__init__.py
run_time_assurance/zoo/integrators/integrator_1d.py
run_time_assurance-1.18.6.dist-info/LICENSE
run_time_assurance-1.18.6.dist-info/METADATA
run_time_assurance-1.18.6.dist-info/WHEEL
run_time_assurance-1.18.6.dist-info/RECORD
