Metadata-Version: 2.1
Name: run-time-assurance
Version: 1.18.6
Summary: The run-time-assurance library provides an interface and implementations for Run Time Assurance (RTA) safety filters.
Home-page: https://github.com/act3-ace/run-time-assurance.git
Author: Charles Keating
Author-email: Charles.Keating@udri.udayton.edu
Requires-Python: >=3.10,<3.13
Classifier: Operating System :: OS Independent
Classifier: Programming Language :: Python :: 3
Classifier: Programming Language :: Python :: 3.10
Classifier: Programming Language :: Python :: 3.11
Classifier: Programming Language :: Python :: 3.12
Requires-Dist: jax[cpu] (>=0.4.30,<0.5.0)
Requires-Dist: matplotlib (>=3.8.0,<4.0.0)
Requires-Dist: numpy (>=2.0.2,<3.0.0)
Requires-Dist: pydantic (>=2.8.0,<3.0.0)
Requires-Dist: pyqt6 (>=6.7.1,<7.0.0)
Requires-Dist: quadprog (>=0.1.11,<0.2.0)
Requires-Dist: safe-autonomy-simulation (>=2.2.0,<3.0.0)
Requires-Dist: scipy (>=1.10.0)
Project-URL: Documentation, https://github.com/act3-ace/run-time-assurance/docs
Project-URL: Repository, https://github.com/act3-ace/run-time-assurance.git
